tasep_models/__init__.py
tasep_models/codon_weights.py
tasep_models/models.py
tasep_models-0.1.0.dist-info/METADATA
tasep_models-0.1.0.dist-info/WHEEL
tasep_models-0.1.0.dist-info/licenses/LICENSE
tasep_models-0.1.0.dist-info/RECORD
