Metadata-Version: 2.4
Name: tasep_models
Version: 0.1.0
Summary: TASEP modeling and simulation library
Author: Luis U. Aguilera
License-Expression: BSD-3-Clause
License-File: LICENSE
Requires-Python: >=3.10
Requires-Dist: biopython>=1.81
Requires-Dist: dna-features-viewer>=3.1
Requires-Dist: joblib>=1.3
Requires-Dist: llvmlite==0.43.0
Requires-Dist: matplotlib==3.9.2
Requires-Dist: numba==0.60.0
Requires-Dist: numpy==1.26.4
Requires-Dist: pandas==2.2.2
Requires-Dist: scipy==1.13.1
Requires-Dist: snapgene-reader>=0.1
